{
    "id": "io.supernova.ios-swiftui",
    "name": "iOS SwiftUI - Public Package",
    "description": "iOS SwiftUI token and style exporter with public access scope",
    "source_dir": "src",
    "version": "1.3.0",
    "usesBrands": true,
    "tags": [
        "iOS",
        "SwiftUI",
        "Tokens",
        "Styles",
        "Colors",
        "Borders",
        "Gradients",
        "Measures",
        "Typography",
        "Radii"
    ],
    "author": "Vaclav Lustek & Jiri Trecak",
    "organization": "Supernova",
    "homepage": "https://supernova.io",
    "config": {
        "output": "output.json",
        "sources": "sources.json",
        "js": "src/functions.js"
    },
    "engines": {
        "pulsar": "1.0.0",
        "supernova": "1.0.0"
    }
}